ptc/__init__.py
ptc/cli.py
ptc/color_opacity_editor.py
ptc/colors.py
ptc/core.py
ptc/dockable_views.py
ptc/file.py
ptc/filters.py
ptc/hover.py
ptc/multiblock.py
ptc/palette.py
ptc/pipeline.py
ptc/representation.py
ptc/reset_camera_button.py
ptc/toolbar.py
ptc/transform_editor.py
ptc/utils.py
ptc/vcr.py
ptc/vuetify.py
ptc/apps/__init__.py
ptc/apps/demo.py
ptc/apps/lite.py
ptc/apps/sphere.py
ptc/apps/state_loader.py
ptc/assets/__init__.py
ptc/assets/http/style.css
ptc/layouts/__init__.py
ptc/layouts/col.py
ptc/layouts/factory.py
ptc/layouts/side.py
ptc/proxy_editor/__init__.py
ptc/proxy_editor/core.py
ptc/proxy_editor/info.py
ptc/proxy_editor/plane.py
ptc/proxy_editor/yaml_editor.py
ptc/views/__init__.py
ptc/views/table.py
ptc/vue2/__init__.py
ptc/vue2/palette.py
ptc/vue2/reset_camera_button.py
paraview_trame_components-0.16.0.dist-info/METADATA
paraview_trame_components-0.16.0.dist-info/WHEEL
paraview_trame_components-0.16.0.dist-info/licenses/LICENSE
paraview_trame_components-0.16.0.dist-info/RECORD
