Metadata-Version: 2.4
Name: paraview-trame-components
Version: 0.16.0
Summary: Macro components for ParaView
Author-email: Sebastien Jourdain <sebastien.jourdain@kitware.com>
Maintainer-email: Sebastien Jourdain <sebastien.jourdain@kitware.com>
License: Copyright 2024 Kitware Inc.
License-File: LICENSE
Keywords: components,paraview,trame,web
Classifier: Development Status :: 4 - Beta
Classifier: Intended Audience :: Developers
Classifier: License :: OSI Approved :: Apache Software License
Classifier: Programming Language :: Python :: 3
Classifier: Programming Language :: Python :: 3.10
Requires-Python: >=3.10
Requires-Dist: pyyaml
Requires-Dist: trame-color-opacity-editor
Requires-Dist: trame-components
Requires-Dist: trame-vtk
Requires-Dist: trame-vuetify
Requires-Dist: trame>=3.10
Provides-Extra: ci
Requires-Dist: build; extra == 'ci'
Requires-Dist: pre-commit; extra == 'ci'
Provides-Extra: dev
Requires-Dist: pre-commit; extra == 'dev'
Requires-Dist: python-semantic-release; extra == 'dev'
Requires-Dist: ruff; extra == 'dev'
Provides-Extra: dockview
Requires-Dist: trame-dockview; extra == 'dockview'
